owl/.env_template
owl/webapp.py
owl/webapp_backup.py
owl/webapp_jp.py
owl/webapp_zh.py
owl/assets/owl-favicon.ico
owl/utils/__init__.py
owl/utils/common.py
owl/utils/document_toolkit.py
owl/utils/enhanced_role_playing.py
owl/utils/gaia.py
mseep_owl-0.0.2.dist-info/METADATA
mseep_owl-0.0.2.dist-info/WHEEL
mseep_owl-0.0.2.dist-info/RECORD
